mtcli_prevsession/__init__.py
mtcli_prevsession/cli.py
mtcli_prevsession/conf.py
mtcli_prevsession/controller.py
mtcli_prevsession/model.py
mtcli_prevsession/plugin.py
mtcli_prevsession/view.py
mtcli_prevsession-1.0.0.dist-info/entry_points.txt
mtcli_prevsession-1.0.0.dist-info/licenses/LICENSE
mtcli_prevsession-1.0.0.dist-info/METADATA
mtcli_prevsession-1.0.0.dist-info/WHEEL
mtcli_prevsession-1.0.0.dist-info/RECORD
