Metadata-Version: 2.4
Name: mtcli-prevsession
Version: 1.0.0
Summary: Plugin mtcli para exibicao de preços do pregão anterior
License-Expression: GPL-3.0
License-File: LICENSE
Author: Valmir França
Author-email: vfranca3@gmail.com
Requires-Python: >=3.10,<3.14
Classifier: Programming Language :: Python :: 3
Classifier: Programming Language :: Python :: 3.10
Classifier: Programming Language :: Python :: 3.11
Classifier: Programming Language :: Python :: 3.12
Classifier: Programming Language :: Python :: 3.13
Requires-Dist: click (>=8.3.0,<9.0.0)
Requires-Dist: metatrader5 (>=5.0.5370,<6.0.0)
Requires-Dist: mtcli (>=3.2.0)
